prymal/__init__.py
prymal/integer_factorization.py
prymal/primality_test.py
prymal/sieve.py
prymal/utils.py
prymal-0.0.1.dist-info/METADATA
prymal-0.0.1.dist-info/WHEEL
prymal-0.0.1.dist-info/licenses/LICENSE
prymal-0.0.1.dist-info/RECORD
