Metadata-Version: 2.3
Name: prymal
Version: 0.0.1
Summary: Prime number functionalities like factorization and primality test in python.
Project-URL: HomePage, https://github.com/haha0512/pyprimes
Project-URL: Issues, https://github.com/haha0512/pyprimes/issues
Author-email: Pilsang Kim <pilsang0512@gmail.com>
License: MIT License
License-File: LICENSE
Classifier: Development Status :: 3 - Alpha
Classifier: Intended Audience :: Developers
Classifier: License :: OSI Approved :: MIT License
Classifier: Operating System :: OS Independent
Classifier: Topic :: Scientific/Engineering :: Mathematics
Requires-Python: >=3.8
